PhpWanquanZhongwenShouceSadly/README.md
PhpWanquanZhongwenShouceSadly/__init__.py
PhpWanquanZhongwenShouceSadly/__main__.py
PhpWanquanZhongwenShouceSadly/file.epub
PhpWanquanZhongwenShouceSadly/index.html
PhpWanquanZhongwenShouceSadly/css/__init__.py
PhpWanquanZhongwenShouceSadly/css/annotations.css
PhpWanquanZhongwenShouceSadly/css/main.css
PhpWanquanZhongwenShouceSadly/css/normalize.css
PhpWanquanZhongwenShouceSadly/css/popup.css
PhpWanquanZhongwenShouceSadly/font/__init__.py
PhpWanquanZhongwenShouceSadly/font/fontello.eot
PhpWanquanZhongwenShouceSadly/font/fontello.svg
PhpWanquanZhongwenShouceSadly/font/fontello.ttf
PhpWanquanZhongwenShouceSadly/font/fontello.woff
PhpWanquanZhongwenShouceSadly/img/__init__.py
PhpWanquanZhongwenShouceSadly/img/annotator-glyph-sprite.png
PhpWanquanZhongwenShouceSadly/img/annotator-icon-sprite.png
PhpWanquanZhongwenShouceSadly/img/apple-touch-icon.png
PhpWanquanZhongwenShouceSadly/img/cancelfullscreen.png
PhpWanquanZhongwenShouceSadly/img/close.png
PhpWanquanZhongwenShouceSadly/img/fullscreen.png
PhpWanquanZhongwenShouceSadly/img/loader.gif
PhpWanquanZhongwenShouceSadly/img/menu-icon.png
PhpWanquanZhongwenShouceSadly/img/save.png
PhpWanquanZhongwenShouceSadly/img/saved.png
PhpWanquanZhongwenShouceSadly/img/settings-s.png
PhpWanquanZhongwenShouceSadly/img/settings.png
PhpWanquanZhongwenShouceSadly/img/star.png
PhpWanquanZhongwenShouceSadly/js/__init__.py
PhpWanquanZhongwenShouceSadly/js/epub.js
PhpWanquanZhongwenShouceSadly/js/epub.min.js
PhpWanquanZhongwenShouceSadly/js/epub.min.map
PhpWanquanZhongwenShouceSadly/js/hooks.min.js
PhpWanquanZhongwenShouceSadly/js/hooks.min.map
PhpWanquanZhongwenShouceSadly/js/reader.js
PhpWanquanZhongwenShouceSadly/js/reader.js.map
PhpWanquanZhongwenShouceSadly/js/reader.min.js
PhpWanquanZhongwenShouceSadly/js/reader.min.map
PhpWanquanZhongwenShouceSadly/js/hooks/__init__.py
PhpWanquanZhongwenShouceSadly/js/hooks/extensions/__init__.py
PhpWanquanZhongwenShouceSadly/js/hooks/extensions/highlight.js
php_wanquan_zhongwen_shouce_sadly-2024.3.2.0.dist-info/METADATA
php_wanquan_zhongwen_shouce_sadly-2024.3.2.0.dist-info/WHEEL
php_wanquan_zhongwen_shouce_sadly-2024.3.2.0.dist-info/entry_points.txt
php_wanquan_zhongwen_shouce_sadly-2024.3.2.0.dist-info/top_level.txt
php_wanquan_zhongwen_shouce_sadly-2024.3.2.0.dist-info/RECORD
